exasol_sagemaker_extension/__init__.py
exasol_sagemaker_extension/autopilot_endpoint_deletion_udf.py
exasol_sagemaker_extension/autopilot_endpoint_deployment_udf.py
exasol_sagemaker_extension/autopilot_job_status_polling_udf.py
exasol_sagemaker_extension/autopilot_prediction_udf.py
exasol_sagemaker_extension/autopilot_training_udf.py
exasol_sagemaker_extension/autopilot_utils/__init__.py
exasol_sagemaker_extension/autopilot_utils/enpoint_deletion.py
exasol_sagemaker_extension/autopilot_utils/enpoint_deployment.py
exasol_sagemaker_extension/autopilot_utils/model_prediction.py
exasol_sagemaker_extension/autopilot_utils/model_training.py
exasol_sagemaker_extension/autopilot_utils/status_polling.py
exasol_sagemaker_extension/deploy.py
exasol_sagemaker_extension/deployment/__init__.py
exasol_sagemaker_extension/deployment/constants.py
exasol_sagemaker_extension/deployment/deploy_create_statements.py
exasol_sagemaker_extension/deployment/generate_create_statement_autopilot_endpoint_deletion.py
exasol_sagemaker_extension/deployment/generate_create_statement_autopilot_endpoint_deployment.py
exasol_sagemaker_extension/deployment/generate_create_statement_autopilot_job_status_polling.py
exasol_sagemaker_extension/deployment/generate_create_statement_autopilot_training.py
exasol_sagemaker_extension/deployment/generate_create_statement_base.py
exasol_sagemaker_extension/deployment/language_container.py
exasol_sagemaker_extension/deployment/regenerate_scripts.py
exasol_sagemaker_extension/deployment/sme_language_container_deployer.py
exasol_sagemaker_extension/lua/src/autopilot_endpoint_deletion.lua
exasol_sagemaker_extension/lua/src/autopilot_endpoint_deployment.lua
exasol_sagemaker_extension/lua/src/autopilot_job_status_polling.lua
exasol_sagemaker_extension/lua/src/autopilot_training_main.lua
exasol_sagemaker_extension/lua/src/aws_s3_handler.lua
exasol_sagemaker_extension/lua/src/aws_sagemaker_handler.lua
exasol_sagemaker_extension/lua/src/db_metadata_reader.lua
exasol_sagemaker_extension-0.11.6.dist-info/METADATA
exasol_sagemaker_extension-0.11.6.dist-info/WHEEL
exasol_sagemaker_extension-0.11.6.dist-info/licenses/LICENSE
exasol_sagemaker_extension-0.11.6.dist-info/RECORD
